pypi_flow/CLS_waterfall.py
pypi_flow/__init__.py
pypi_flow/packageTemplate/.gitignore
pypi_flow/packageTemplate/MANIFEST.in
pypi_flow/packageTemplate/PipLocalUninstall.py
pypi_flow/packageTemplate/PipLocalUpgrade.py
pypi_flow/packageTemplate/PypiUpload.py
pypi_flow/packageTemplate/README.md
pypi_flow/packageTemplate/setup.py
pypi_flow/packageTemplate/LicenseTemplates/MIT.txt
pypi_flow/packageTemplate/package_name/__init__.py
pypi_flow/packageTemplate/package_name/__pycache__/__init__.cpython-37.pyc
pypi_flow-19.8.0.data/scripts/waterfall.py
pypi_flow-19.8.0.dist-info/LICENSE
pypi_flow-19.8.0.dist-info/METADATA
pypi_flow-19.8.0.dist-info/WHEEL
pypi_flow-19.8.0.dist-info/entry_points.txt
pypi_flow-19.8.0.dist-info/top_level.txt
pypi_flow-19.8.0.dist-info/RECORD
