Metadata-Version: 2.1
Name: pypi-flow
Version: 19.8.0
Summary: Create and upload new packages to PyPI within seconds.
Home-page: https://github.com/ZenosParadox/pypi_flow
Author: Gabriel Rosales
Author-email: gabriel.alejandro.rosales@gmail.com
License: UNKNOWN
Platform: UNKNOWN
Classifier: Programming Language :: Python :: 3
Classifier: License :: OSI Approved :: MIT License
Classifier: Operating System :: OS Independent
Requires-Dist: grtoolkit
